gcp_iam/__init__.py
gcp_iam/__main__.py
gcp_iam/server.py
gcp_iam-0.2.0.dist-info/METADATA
gcp_iam-0.2.0.dist-info/WHEEL
gcp_iam-0.2.0.dist-info/entry_points.txt
gcp_iam-0.2.0.dist-info/RECORD
