Metadata-Version: 2.4
Name: gcp-iam
Version: 0.2.0
Summary: MCP Server for GCP IAM
Requires-Python: >=3.13
Requires-Dist: dotenv
Requires-Dist: google-cloud-iam
Requires-Dist: google-cloud-storage
Requires-Dist: mcp
Requires-Dist: pydantic
